common/__init__.py
common/geometry.py
common/hamiltonian.py
common/molecule_viz.py
common/molecules.py
common/naming.py
common/paths.py
common/persist.py
common/plotting.py
qite/__init__.py
qite/__main__.py
qite/core.py
qite/engine.py
qite/hamiltonian.py
qite/io_utils.py
qite/visualize.py
qpe/__init__.py
qpe/__main__.py
qpe/core.py
qpe/hamiltonian.py
qpe/io_utils.py
qpe/noise.py
qpe/visualize.py
vqe/__init__.py
vqe/__main__.py
vqe/ansatz.py
vqe/core.py
vqe/engine.py
vqe/hamiltonian.py
vqe/io_utils.py
vqe/optimizer.py
vqe/ssvqe.py
vqe/visualize.py
vqe/vqd.py
vqe_pennylane-0.3.0.dist-info/licenses/LICENSE
vqe_pennylane-0.3.0.dist-info/METADATA
vqe_pennylane-0.3.0.dist-info/WHEEL
vqe_pennylane-0.3.0.dist-info/entry_points.txt
vqe_pennylane-0.3.0.dist-info/top_level.txt
vqe_pennylane-0.3.0.dist-info/RECORD
