Metadata-Version: 2.4
Name: vqe-pennylane
Version: 0.3.0
Summary: Quantum Simulation Suite with VQE, QPE, and QITE modules (PennyLane-based)
Author-email: Sid Richards <siddrichards@hotmail.co.uk>
License-Expression: MIT
Project-URL: Homepage, https://github.com/SidRichardsQuantum/Variational_Quantum_Eigensolver
Project-URL: Issues, https://github.com/SidRichardsQuantum/Variational_Quantum_Eigensolver/issues
Project-URL: Documentation, https://github.com/SidRichardsQuantum/Variational_Quantum_Eigensolver#readme
Keywords: quantum,VQE,QPE,QITE,simulation,pennylane,quantum-chemistry
Classifier: Development Status :: 4 - Beta
Classifier: Intended Audience :: Science/Research
Classifier: Operating System :: OS Independent
Classifier: Programming Language :: Python :: 3
Classifier: Programming Language :: Python :: 3.10
Classifier: Programming Language :: Python :: 3.11
Classifier: Programming Language :: Python :: 3.12
Classifier: Topic :: Scientific/Engineering :: Physics
Requires-Python: >=3.10
License-File: LICENSE
Requires-Dist: pennylane<0.45,>=0.42
Requires-Dist: numpy<2.0,>=1.23
Requires-Dist: scipy<2.0,>=1.10
Requires-Dist: matplotlib
Requires-Dist: openfermion
Requires-Dist: openfermionpyscf
Provides-Extra: dev
Requires-Dist: pytest>=8.0; extra == "dev"
Requires-Dist: black==26.1.0; extra == "dev"
Requires-Dist: ruff==0.14.11; extra == "dev"
Requires-Dist: mypy; extra == "dev"
Provides-Extra: docs
Requires-Dist: sphinx; extra == "docs"
Requires-Dist: furo; extra == "docs"
Dynamic: license-file
